topoptlab/__init__.py
topoptlab/accelerators.py
topoptlab/amg.py
topoptlab/design_analysis.py
topoptlab/draw_functions.py
topoptlab/fdm.py
topoptlab/fem.py
topoptlab/geometries.py
topoptlab/geometry_parser.py
topoptlab/gmg.py
topoptlab/linear_solvers.py
topoptlab/log_utils.py
topoptlab/material_interpolation.py
topoptlab/multigrid.py
topoptlab/objectives.py
topoptlab/output_designs.py
topoptlab/rotation_matrices.py
topoptlab/solve_linsystem.py
topoptlab/stiffness_tensors.py
topoptlab/timestepper.py
topoptlab/topology_optimization.py
topoptlab/utils.py
topoptlab/blocksparse/blockdiagonal.py
topoptlab/blocksparse/make_blocks.py
topoptlab/bounds/README.md
topoptlab/bounds/hashin_rosen_3d.py
topoptlab/bounds/hashin_shtrikman_2d.py
topoptlab/bounds/hashin_shtrikman_3d.py
topoptlab/bounds/voigt_reuss.py
topoptlab/elements/bilinear_quadrilateral.py
topoptlab/elements/bodyforce_2d.py
topoptlab/elements/bodyforce_3d.py
topoptlab/elements/heatexpansion_2d.py
topoptlab/elements/heatexpansion_3d.py
topoptlab/elements/isoparam_mapping.py
topoptlab/elements/linear_elasticity_2d.py
topoptlab/elements/linear_elasticity_3d.py
topoptlab/elements/linear_interval.py
topoptlab/elements/mass_scalar_2d.py
topoptlab/elements/mass_scalar_3d.py
topoptlab/elements/mass_vector_2d.py
topoptlab/elements/mass_vector_3d.py
topoptlab/elements/monomial_scalar_2d.py
topoptlab/elements/monomial_scalar_3d.py
topoptlab/elements/poisson_2d.py
topoptlab/elements/poisson_3d.py
topoptlab/elements/screenedpoisson_2d.py
topoptlab/elements/screenedpoisson_3d.py
topoptlab/elements/strain_measures.py
topoptlab/elements/trilinear_hexahedron.py
topoptlab/elements/volume_integral.py
topoptlab/example_bc/heat_conduction.py
topoptlab/example_bc/lin_elast.py
topoptlab/filter/amfilter_langelaar.py
topoptlab/filter/convolution_filter.py
topoptlab/filter/density_filter.py
topoptlab/filter/fetch_filter.py
topoptlab/filter/filter.py
topoptlab/filter/haeviside_projection.py
topoptlab/filter/haeviside_projectors.py
topoptlab-1.0.0.dist-info/licenses/LICENSE
topoptlab-1.0.0.dist-info/WHEEL
topoptlab-1.0.0.dist-info/METADATA
topoptlab-1.0.0.dist-info/RECORD
