Metadata-Version: 2.4
Name: topoptlab
Version: 1.0.0
Summary: topology optimization for testing and demonstration uses.
Author-email: Stefan Hiemer <stefan.hiemer@unimi.it>
Requires-Python: >=3.12.4
Classifier: Development Status :: 2 - Pre-Alpha
Classifier: Programming Language :: Python
License-File: LICENSE
Requires-Dist: numpy
Requires-Dist: matplotlib
Requires-Dist: scipy
Requires-Dist: cvxopt
Requires-Dist: gmsh
Requires-Dist: mmapy
Requires-Dist: meshio
Requires-Dist: symfem
Requires-Dist: pyamg
Requires-Dist: sphinx>=7.0 ; extra == "docs"
Requires-Dist: sphinx-rtd-theme>=1.3 ; extra == "docs"
Requires-Dist: myst-parser>=2.0 ; extra == "docs"
Requires-Dist: sphinx-autodoc-typehints ; extra == "docs"
Requires-Dist: sphinxcontrib.bibtex ; extra == "docs"
Requires-Dist: linkify-it-py ; extra == "docs"
Requires-Dist: build ; extra == "pypi"
Requires-Dist: twine ; extra == "pypi"
Requires-Dist: pytest ; extra == "tests"
Provides-Extra: docs
Provides-Extra: pypi
Provides-Extra: tests
